micro_smart_hub/__init__.py
micro_smart_hub/automation.py
micro_smart_hub/device.py
micro_smart_hub/scheduler.py
micro_smart_hub/automations/__init__.py
micro_smart_hub/automations/irrigation.py
micro_smart_hub/devices/__init__.py
micro_smart_hub/devices/blebox/__init__.py
micro_smart_hub/devices/blebox/switchbox.py
micro_smart_hub-0.1.9.dist-info/LICENSE
micro_smart_hub-0.1.9.dist-info/METADATA
micro_smart_hub-0.1.9.dist-info/WHEEL
micro_smart_hub-0.1.9.dist-info/top_level.txt
micro_smart_hub-0.1.9.dist-info/RECORD
