Metadata-Version: 2.1
Name: micro-smart-hub
Version: 0.1.9
Summary: A small smart hub building blocks package
Home-page: https://github.com/AleksanderStanikHE/micro-smart-hub.git
Author: Aleksander Stanik (Olek)
Author-email: aleksander.stanik@hammerheadsengineers.com
Classifier: Programming Language :: Python :: 3
Classifier: License :: OSI Approved :: MIT License
Classifier: Operating System :: OS Independent
Requires-Python: >=3.7
License-File: LICENSE
Requires-Dist: flake8
Requires-Dist: numpy
Requires-Dist: requests
Requires-Dist: pyyaml
Requires-Dist: micro-registry
